[  
    {  
      "姓名": "李白",  
      "出生年份": 701,  
      "逝世年份": 762  
    },  
    {  
      "姓名": "杜甫",  
      "出生年份": 712,  
      "逝世年份": 770  
    },  
    {  
      "姓名": "王维",  
      "出生年份": 701,  
      "逝世年份": 761  
    },  
    {  
      "姓名": "岑参",  
      "出生年份": 718,  
      "逝世年份": 769  
    },  
    {  
      "姓名": "韩愈",  
      "出生年份": 768,  
      "逝世年份": 824  
    },  
    {  
      "姓名": "柳宗元",  
      "出生年份": 773,  
      "逝世年份": 819  
    },  
    {  
      "姓名": "刘禹锡",  
      "出生年份": 772,  
      "逝世年份": 842  
    },  
    {  
      "姓名": "白居易",  
      "出生年份": 772,  
      "逝世年份": 846  
    },  
    {  
      "姓名": "元稹",  
      "出生年份": 779,  
      "逝世年份": 831  
    },  
    {  
      "姓名": "贾岛",  
      "出生年份": 779,  
      "逝世年份": 843  
    },  
    {  
      "姓名": "李贺",  
      "出生年份": 790,  
      "逝世年份": 816  
    },  
    {  
      "姓名": "孟郊",  
      "出生年份": 751,  
      "逝世年份": 814  
    },  
    {  
      "姓名": "陈子昂",  
      "出生年份": 661,  
      "逝世年份": 702  
    },  
    {  
      "姓名": "张九龄",  
      "出生年份": 678,  
      "逝世年份": 740  
    },  
    {  
      "姓名": "王之涣",  
      "出生年份": 688,  
      "逝世年份": 742  
    },  
    {  
      "姓名": "李煜",  
      "出生年份": 937,  
      "逝世年份": 978  
    },  
    {  
      "姓名": "王勃",  
      "出生年份": 650,  
      "逝世年份": 676  
    },  
    {  
      "姓名": "骆宾王",  
      "出生年份": 619,  
      "逝世年份": 687  
    },  
    {  
      "姓名": "高适",  
      "出生年份": 704,  
      "逝世年份": 765  
    },  
    {  
      "姓名": "韦应物",  
      "出生年份": 737,  
      "逝世年份": 792  
    },  
    {  
      "姓名": "杜荀鹤",  
      "出生年份": 846,  
      "逝世年份": 904  
    },  
    {  
      "姓名": "李商隐",  
      "出生年份": 813,  
      "逝世年份": 858  
    },  
    {  
      "姓名": "罗隐",  
      "出生年份": 833,  
      "逝世年份": 909  
    },  
    {  
      "姓名": "许浑",  
      "出生年份": 791,  
      "逝世年份": 858  
    },  
    {  
      "姓名": "皮日休",  
      "出生年份": 834,  
      "逝世年份": 883
	}
]